likeapp/__init__.py
likeapp/anyio.py
likeapp/applications.py
likeapp/logger.py
likeapp/utils.py
likeapp/enums/__init__.py
likeapp/enums/match.py
likeapp/ext/telegram/application.py
likeapp/ext/telegram/router.py
likeapp/filters/__init__.py
likeapp/filters/filter.py
likeapp/middleware/__init__.py
likeapp/middleware/base.py
likeapp/middleware/exception.py
likeapp/middleware/manager.py
likeapp/routing/__init__.py
likeapp/routing/route.py
likeapp/routing/router.py
likeapp/types/__init__.py
likeapp/types/decorated.py
likeapp/types/event.py
likeapp/types/filter.py
likeapp-1.1.dist-info/METADATA
likeapp-1.1.dist-info/WHEEL
likeapp-1.1.dist-info/licenses/LICENSE
likeapp-1.1.dist-info/RECORD
